MANIFEST.in
README.md
setup.py
bin/speriment-output
doc/speriment.html
speriment/__init__.py
speriment/compiler.py
speriment/utils.py
speriment.egg-info/PKG-INFO
speriment.egg-info/SOURCES.txt
speriment.egg-info/dependency_links.txt
speriment.egg-info/not-zip-safe
speriment.egg-info/requires.txt
speriment.egg-info/top_level.txt
speriment/components/__init__.py
speriment/components/block.py
speriment/components/component.py
speriment/components/experiment.py
speriment/components/option.py
speriment/components/page.py
speriment/components/resource.py
speriment/components/run_if.py
speriment/components/sample_from.py
speriment/components/sperimentschema.json