Metadata-Version: 1.1
Name: speriment
Version: 0.8.2
Summary: Making experiments easier to express
Home-page: http://github.com/presleyp/speriment
Author: Presley Pizzo
Author-email: ppizzo@linguist.umass.edu
License: GPL 2
Keywords: experiments psychology linguistics
Platform: UNKNOWN
Classifier: Programming Language :: Python :: 2.7
